MANIFEST.in
README.md
requirements.txt
setup.py
tests-requirements.txt
example/__init__.py
example/app.py
example/app_test.py
example/static/favicon.ico
example/templates/example.html
example/templates/index.html
example/templates/flacon/base.html
flacon/__init__.py
flacon/flacon.py
flacon/flacon_test.py
flacon/testutils.py
flacon.egg-info/PKG-INFO
flacon.egg-info/SOURCES.txt
flacon.egg-info/dependency_links.txt
flacon.egg-info/entry_points.txt
flacon.egg-info/not-zip-safe
flacon.egg-info/requires.txt
flacon.egg-info/top_level.txt
flacon/templates/flacon/_base.html
flacon/templates/flacon/base.html
flacon/templates/flacon/status.html
flacon/templates/flacon/threads.html