Metadata-Version: 2.1
Name: flacon
Version: 0.3.4
Summary: Flask(-Twisted) microframework for microservices with Prometheus and Sentry support.
Home-page: https://github.com/criteo/flacon/
Author: Corentin Chary
Author-email: corentin.chary@gmail.com
License: Apache 2
Project-URL: Source Code, https://github.com/criteo/flacon/
Keywords: flask twisted gunicorn microframework microservice prometheus sentry
Platform: UNKNOWN
Classifier: Environment :: Web Environment
Classifier: Intended Audience :: Developers
Classifier: Intended Audience :: System Administrators
Classifier: License :: OSI Approved :: Apache Software License
Classifier: Programming Language :: Python :: 2.7
Classifier: Programming Language :: Python :: 3.5
Classifier: Programming Language :: Python :: 3.6
Classifier: Programming Language :: Python :: 3.7
Provides-Extra: twisted
Provides-Extra: gunicorn
